ignite/__init__.py
ignite/_utils.py
ignite/exceptions.py
ignite/py.typed
ignite/utils.py
ignite/base/__init__.py
ignite/base/mixins.py
ignite/contrib/__init__.py
ignite/contrib/engines/__init__.py
ignite/contrib/engines/common.py
ignite/contrib/engines/tbptt.py
ignite/contrib/handlers/__init__.py
ignite/contrib/handlers/base_logger.py
ignite/contrib/handlers/clearml_logger.py
ignite/contrib/handlers/lr_finder.py
ignite/contrib/handlers/mlflow_logger.py
ignite/contrib/handlers/neptune_logger.py
ignite/contrib/handlers/param_scheduler.py
ignite/contrib/handlers/polyaxon_logger.py
ignite/contrib/handlers/tensorboard_logger.py
ignite/contrib/handlers/time_profilers.py
ignite/contrib/handlers/tqdm_logger.py
ignite/contrib/handlers/visdom_logger.py
ignite/contrib/handlers/wandb_logger.py
ignite/contrib/metrics/__init__.py
ignite/contrib/metrics/average_precision.py
ignite/contrib/metrics/cohen_kappa.py
ignite/contrib/metrics/gpu_info.py
ignite/contrib/metrics/precision_recall_curve.py
ignite/contrib/metrics/roc_auc.py
ignite/contrib/metrics/regression/__init__.py
ignite/contrib/metrics/regression/_base.py
ignite/contrib/metrics/regression/canberra_metric.py
ignite/contrib/metrics/regression/fractional_absolute_error.py
ignite/contrib/metrics/regression/fractional_bias.py
ignite/contrib/metrics/regression/geometric_mean_absolute_error.py
ignite/contrib/metrics/regression/geometric_mean_relative_absolute_error.py
ignite/contrib/metrics/regression/manhattan_distance.py
ignite/contrib/metrics/regression/maximum_absolute_error.py
ignite/contrib/metrics/regression/mean_absolute_relative_error.py
ignite/contrib/metrics/regression/mean_error.py
ignite/contrib/metrics/regression/mean_normalized_bias.py
ignite/contrib/metrics/regression/median_absolute_error.py
ignite/contrib/metrics/regression/median_absolute_percentage_error.py
ignite/contrib/metrics/regression/median_relative_absolute_error.py
ignite/contrib/metrics/regression/r2_score.py
pytorch_ignite-0.5.3.dist-info/METADATA
pytorch_ignite-0.5.3.dist-info/WHEEL
pytorch_ignite-0.5.3.dist-info/licenses/LICENSE
pytorch_ignite-0.5.3.dist-info/RECORD
