Metadata-Version: 2.4
Name: pytorch-ignite
Version: 0.5.3
Summary: A lightweight library to help with training neural networks in PyTorch.
Project-URL: Homepage, https://pytorch-ignite.ai
Project-URL: Repository, https://github.com/pytorch/ignite
Author-email: PyTorch-Ignite Team <contact@pytorch-ignite.ai>
License-Expression: BSD-3-Clause
License-File: LICENSE
Classifier: Programming Language :: Python :: 3
Requires-Python: <=3.13,>=3.9
Requires-Dist: packaging
Requires-Dist: torch<3,>=1.10
